supervisor_testing/__init__.py
supervisor_testing/data.py
supervisor_testing/loading.py
supervisor_testing/modules.py
supervisor_testing/models/adult-ffn-tf1.15.2.h5
supervisor_testing/models/iris-ae-tf1.15.2.h5
supervisor_testing/models/iris-enc-tf1.15.2.h5
supervisor_testing/models/iris-ffn-tf1.15.2.h5
supervisor_testing/models/mnist-cnn-pt1.9.1.pt
supervisor_testing/models/mnist-cnn-tf1.15.2.h5
supervisor_testing/models/mnist-logistic-tf1.15.2.h5
supervisor_testing/models/adult-ffn-tf2.2.0/saved_model.pb
supervisor_testing/models/adult-ffn-tf2.2.0/variables/variables.data-00000-of-00001
supervisor_testing/models/adult-ffn-tf2.2.0/variables/variables.index
supervisor_testing/models/iris-ae-tf2.2.0/saved_model.pb
supervisor_testing/models/iris-ae-tf2.2.0/variables/variables.data-00000-of-00001
supervisor_testing/models/iris-ae-tf2.2.0/variables/variables.index
supervisor_testing/models/iris-enc-tf2.2.0/saved_model.pb
supervisor_testing/models/iris-enc-tf2.2.0/variables/variables.data-00000-of-00001
supervisor_testing/models/iris-enc-tf2.2.0/variables/variables.index
supervisor_testing/models/iris-ffn-tf2.2.0/saved_model.pb
supervisor_testing/models/iris-ffn-tf2.2.0/variables/variables.data-00000-of-00001
supervisor_testing/models/iris-ffn-tf2.2.0/variables/variables.index
supervisor_testing/models/mnist-cnn-tf2.2.0/saved_model.pb
supervisor_testing/models/mnist-cnn-tf2.2.0/variables/variables.data-00000-of-00001
supervisor_testing/models/mnist-cnn-tf2.2.0/variables/variables.index
supervisor_testing/models/mnist-logistic-tf2.2.0/saved_model.pb
supervisor_testing/models/mnist-logistic-tf2.2.0/variables/variables.data-00000-of-00001
supervisor_testing/models/mnist-logistic-tf2.2.0/variables/variables.index
supervisor_testing-0.1.0.dist-info/METADATA
supervisor_testing-0.1.0.dist-info/WHEEL
supervisor_testing-0.1.0.dist-info/top_level.txt
supervisor_testing-0.1.0.dist-info/RECORD
