Metadata-Version: 2.1
Name: supervisor-testing
Version: 0.1.0
Summary: UNKNOWN
Home-page: UNKNOWN
License: UNKNOWN
Platform: UNKNOWN
Requires-Python: >=3.7
Provides-Extra: training
Requires-Dist: numpy <2.0.0,>=1.16.2 ; extra == 'training'
Requires-Dist: pandas <2.0.0,>=0.23.3 ; extra == 'training'
Requires-Dist: requests <3.0.0,>=2.21.0 ; extra == 'training'
Requires-Dist: scikit-learn <2.0.0,>=0.20.2 ; extra == 'training'
Requires-Dist: tensorflow !=2.6.0,!=2.6.1,<2.11.0,>=2.0.0 ; extra == 'training'
Requires-Dist: torch <2.0.0,>=1.9.0 ; extra == 'training'
Requires-Dist: torchvision <1.0.0,>=0.10.0 ; extra == 'training'
